opentools1/__init__.py
opentools1/tool.py
opentools1-0.0.1.dist-info/METADATA
opentools1-0.0.1.dist-info/WHEEL
opentools1-0.0.1.dist-info/licenses/LICENSE
opentools1-0.0.1.dist-info/RECORD
